asl_workflow_engine/__init__.py
asl_workflow_engine/amqp_0_9_1_messaging.py
asl_workflow_engine/amqp_0_9_1_messaging_asyncio.py
asl_workflow_engine/arn.py
asl_workflow_engine/asl_exceptions.py
asl_workflow_engine/event_dispatcher.py
asl_workflow_engine/logger.py
asl_workflow_engine/messaging_exceptions.py
asl_workflow_engine/metrics_summary.py
asl_workflow_engine/metrics_system.py
asl_workflow_engine/open_tracing_factory.py
asl_workflow_engine/rest_api.py
asl_workflow_engine/rest_api_asyncio.py
asl_workflow_engine/state_engine.py
asl_workflow_engine/state_engine_paths.py
asl_workflow_engine/store.py
asl_workflow_engine/task_dispatcher.py
asl_workflow_engine/workflow_engine.py
local_workflow_engine/__init__.py
local_workflow_engine/amqp_0_9_1_messaging.py
local_workflow_engine/amqp_0_9_1_messaging_asyncio.py
local_workflow_engine/arn.py
local_workflow_engine/asl_exceptions.py
local_workflow_engine/event_dispatcher.py
local_workflow_engine/logger.py
local_workflow_engine/messaging_exceptions.py
local_workflow_engine/metrics_summary.py
local_workflow_engine/metrics_system.py
local_workflow_engine/open_tracing_factory.py
local_workflow_engine/rest_api.py
local_workflow_engine/rest_api_asyncio.py
local_workflow_engine/state_engine.py
local_workflow_engine/state_engine_paths.py
local_workflow_engine/store.py
local_workflow_engine/task_dispatcher.py
local_workflow_engine/workflow_engine.py
test/__init__.py
test/blocking_processor_state_machine.py
test/error_handling1.py
test/error_handling2.py
test/error_handling3.py
test/id_then_unzip.py
test/iterate1.py
test/iterate2.py
test/map1.py
test/map2.py
test/map3.py
test/parallel1.py
test/parallel2.py
test/producer_consumer.py
test/producer_consumer_asyncio.py
test/producer_consumer_asyncio_expiration.py
test/producer_consumer_asyncio_headers.py
test/producer_consumer_asyncio_topic.py
test/simple_state_machine1.py
test/simple_state_machine2.py
test/step_by_step.py
test/subscribe_to_notifications.py
local_workflow_engine-1.0.4.dist-info/METADATA
local_workflow_engine-1.0.4.dist-info/WHEEL
local_workflow_engine-1.0.4.dist-info/top_level.txt
local_workflow_engine-1.0.4.dist-info/RECORD
