Metadata-Version: 2.1
Name: local-workflow-engine
Version: 1.0.4
Summary: A workflow engine based on the Amazon States Language (ASL).
Home-page: UNKNOWN
Author: UNKNOWN
Author-email: UNKNOWN
License: UNKNOWN
Platform: UNKNOWN
Requires-Dist: pika
Requires-Dist: structlog
Requires-Dist: ujson
Requires-Dist: jsonpath
Requires-Dist: flask
Requires-Dist: quart
Requires-Dist: redis
Requires-Dist: pottery
Requires-Dist: opentracing (>=2.2)
Requires-Dist: aioprometheus
Requires-Dist: jaeger-client
